dyngle/__init__.py
dyngle/__main__.py
dyngle/command/__init__.py
dyngle/command/list_operations_command.py
dyngle/command/mcp_command.py
dyngle/command/run_command.py
dyngle/error.py
dyngle/model/__init__.py
dyngle/model/context.py
dyngle/model/expression.py
dyngle/model/interface.py
dyngle/model/operation.py
dyngle/model/template.py
dyngle/model/toolset.py
dyngle/model/util.py
dyngle/servers/__init__.py
dyngle/servers/mcp_server.py
dyngle-2.12.3.dist-info/METADATA
dyngle-2.12.3.dist-info/WHEEL
dyngle-2.12.3.dist-info/entry_points.txt
dyngle-2.12.3.dist-info/RECORD
