Metadata-Version: 2.4
Name: dyngle
Version: 2.12.3
Summary: Run lightweight local workflows
License: MIT
Author: Steampunk Wizard
Author-email: dyngle@steamwiz.io
Requires-Python: >=3.13,<4.0
Classifier: License :: OSI Approved :: MIT License
Classifier: Programming Language :: Python :: 3
Classifier: Programming Language :: Python :: 3.13
Classifier: Programming Language :: Python :: 3.14
Requires-Dist: black (>=25.11.0,<26.0.0)
Requires-Dist: jsonschema (>=4.25.0,<5.0.0)
Requires-Dist: mcp (>=1.23.1,<2.0.0)
Requires-Dist: requests (>=2.32.3,<3.0.0)
Requires-Dist: wizlib (>=3.3.11,<3.4.0)
